src/__init__.py
src/server.py
src/model/request/__init__.py
src/model/request/wikipedia_search.py
src/model/response/__init__.py
src/model/response/wikipedia_detail.py
src/model/response/wikipedia_search_result.py
wiki_mcp-0.0.5.dist-info/METADATA
wiki_mcp-0.0.5.dist-info/WHEEL
wiki_mcp-0.0.5.dist-info/entry_points.txt
wiki_mcp-0.0.5.dist-info/RECORD
