Metadata-Version: 2.4
Name: wiki-mcp
Version: 0.0.5
Summary: 위키피디아 mcp server
Author-email: hero <icraft2170@gmail.com>
License: MIT
Requires-Python: >=3.10
Requires-Dist: beautifulsoup4>=4.12.0
Requires-Dist: mcp[cli]>=1.6.0
Requires-Dist: twine>=6.1.0
